bitbucket_mcp_cloud/__init__.py
bitbucket_mcp_cloud/models.py
bitbucket_mcp_cloud/utils.py
server.py
bitbucket_mcp_cloud-1.3.7.dist-info/METADATA
bitbucket_mcp_cloud-1.3.7.dist-info/WHEEL
bitbucket_mcp_cloud-1.3.7.dist-info/entry_points.txt
bitbucket_mcp_cloud-1.3.7.dist-info/RECORD
