Metadata-Version: 2.4
Name: bitbucket-mcp-cloud
Version: 1.3.7
Summary: A Model Context Protocol (MCP) server for Bitbucket Cloud API integration
Project-URL: Homepage, https://github.com/jhonymiler/Bitbucket-MCP-Server-Cloud
Project-URL: Documentation, https://github.com/jhonymiler/Bitbucket-MCP-Server-Cloud#readme
Project-URL: Repository, https://github.com/jhonymiler/Bitbucket-MCP-Server-Cloud
Project-URL: Issues, https://github.com/jhonymiler/Bitbucket-MCP-Server-Cloud/issues
Author-email: Jhony Miler <jhonymiler@gmail.com>
License: MIT
Keywords: api,bitbucket,mcp,model-context-protocol
Classifier: Development Status :: 4 - Beta
Classifier: Intended Audience :: Developers
Classifier: License :: OSI Approved :: MIT License
Classifier: Programming Language :: Python :: 3
Classifier: Programming Language :: Python :: 3.10
Classifier: Programming Language :: Python :: 3.11
Classifier: Programming Language :: Python :: 3.12
Requires-Python: >=3.10
Requires-Dist: httpx>=0.28.1
Requires-Dist: mcp[cli]>=1.0.0
Requires-Dist: pydantic>=2.10.3
Requires-Dist: python-dotenv>=1.1.0
Provides-Extra: dev
Requires-Dist: black>=24.0.0; extra == 'dev'
Requires-Dist: build>=1.0.0; extra == 'dev'
Requires-Dist: mypy>=1.13.0; extra == 'dev'
Requires-Dist: pytest-asyncio>=0.24.0; extra == 'dev'
Requires-Dist: pytest-cov>=6.0.0; extra == 'dev'
Requires-Dist: pytest-mock>=3.14.0; extra == 'dev'
Requires-Dist: pytest>=8.3.4; extra == 'dev'
Requires-Dist: twine>=4.0.0; extra == 'dev'
